autoscan/__init__.py
autoscan/autoscan.py
autoscan/cli.py
autoscan/common.py
autoscan/config.py
autoscan/errors.py
autoscan/image_processing.py
autoscan/llm_processors/__init__.py
autoscan/llm_processors/base_llm_processor.py
autoscan/llm_processors/img_to_md_processor.py
autoscan/llm_processors/markdown_consolidator.py
autoscan/prompts.py
autoscan/types.py
autoscan/utils/__init__.py
autoscan/utils/env.py
autoscan/utils/llm.py
autoscan-0.1.1.dist-info/LICENSE
autoscan-0.1.1.dist-info/METADATA
autoscan-0.1.1.dist-info/WHEEL
autoscan-0.1.1.dist-info/entry_points.txt
autoscan-0.1.1.dist-info/RECORD
