Metadata-Version: 2.1
Name: autoscan
Version: 0.1.1
Summary: High fidelity PDF to Markdown conversion using LLMs (GPT-4o, Gemini, etc.)
Home-page: https://github.com/umermansoor/autoscan
License: MIT
Keywords: pdf,markdown,ocr,llm,document-conversion,ai,gpt,gemini
Author: Umer Mansoor
Author-email: umermk3@gmail.com
Requires-Python: >=3.12,<4.0
Classifier: Development Status :: 4 - Beta
Classifier: Intended Audience :: Developers
Classifier: Intended Audience :: End Users/Desktop
Classifier: License :: OSI Approved :: MIT License
Classifier: Operating System :: OS Independent
Classifier: Programming Language :: Python :: 3
Classifier: Programming Language :: Python :: 3.12
Classifier: Topic :: Scientific/Engineering :: Artificial Intelligence
Classifier: Topic :: Text Processing :: Markup
Classifier: Topic :: Utilities
Requires-Dist: aiofiles (>=24.1.0,<25.0.0)
Requires-Dist: litellm (==1.67.1)
Requires-Dist: pdf2image (>=1.17.0,<2.0.0)
Project-URL: Documentation, https://github.com/umermansoor/autoscan#readme
Project-URL: Repository, https://github.com/umermansoor/autoscan
